sussyfetch/__init__.py
sussyfetch/animations.py
sussyfetch/ascii_art.py
sussyfetch/cli.py
sussyfetch/sus_phrases.py
sussyfetch/system_info.py
sussyfetch-1.0.dist-info/LICENSE
sussyfetch-1.0.dist-info/METADATA
sussyfetch-1.0.dist-info/WHEEL
sussyfetch-1.0.dist-info/entry_points.txt
sussyfetch-1.0.dist-info/top_level.txt
sussyfetch-1.0.dist-info/RECORD
