Metadata-Version: 2.1
Name: sussyfetch
Version: 1.0
Summary: ඞ Fetching system information in style
Home-page: https://github.com/cytronicoder/sussyfetch
Author: Zeyu Yao
Author-email: novodoodle@gmail.com
License: MIT
Classifier: Programming Language :: Python :: 3
Classifier: License :: OSI Approved :: MIT License
Classifier: Operating System :: OS Independent
Requires-Python: >=3.6
License-File: LICENSE
Requires-Dist: rich
Requires-Dist: psutil
Requires-Dist: argparse
